{
    "commandRequirementsNotAFactionLeader": "&cCette commande exige que l'exécuteur soit un chef de faction.",
    "commandRequirementsNotEnoughMoneyInBank": "&cVotre banque ne dispose pas des $%1$s nécessaires pour exécuter cette commande, déposez plus.",
    "commandRequirementsPlayerDoesNotHavePermission": "&cCette commande nécessite l'autorisation %1$s",
    "commandPaidFor": "&7Vous avez payé $%1$s de votre banque pour exécuter cette commande.",
    "commandAdminBaseHelp": "&7La commande de base pour les administrateurs de serveur.",
    "commandAdminBaseHelpMessage": "&aVeuillez exécuter /fax help",
    "commandBaseHelpMessage": "&aVeuillez exécuter /f help.",
    "commandHelpGeneratorPageInvalid": "&cLa page %1$s n'existe pas.",
    "commandHelpGeneratorFormat": "&6/%1$s %2$s &8> &7 %3$s",
    "commandHelpGeneratorBackgroundColor": "GRIS",
    "commandHelpGeneratorNotRequired": "&cNon&r",
    "commandHelpGeneratorRequires": "&aOui&r",
    "commandHelpGeneratorFactionRequired": "&7Membre de la faction requis: %1$s",
    "commandHelpGeneratorClickMeToPaste": "&7Clique pour autocompléter.",
    "commandHelpGeneratorGoTopage": "&7Aller à la page &6%1$s&7.",
    "commandHelpGeneratorPageNavBack": "&6<<<",
    "commandHelpGeneratorPageNavNext": "&6>>>",
    "commandEngineFormatHoverable": "&7&o((Hoverable))&r",
    "commandEngineFormatPrefix": " /%1$s %2$s",
    "commandEngineFormatRequiredArg": "<%1$s>",
    "commandEngineFormatRequiredTooltip": "Cette argument est requis.",
    "commandEngineFormatOptionalArg": "(%1$s)",
    "commandEngineFormatOptionalTooltip": "L'argument est optionnel",
    "commandAdminPowerInvalidPowerTarget": "Cible de pouvoir invalide, utilisé &6current&7 ou &6max",
    "commandAdminPowerHelp": "Gérer le pouvoir d'un joueur",
    "commandAdminPowerSetHelp": "définir la puissance d'un joueur",
    "commandAdminKickNotInFaction": "&7Le joueur &6%1$s&7 ne fais pas parti d'une faction.",
    "commandUpgradeHelp": "afficher le menu principal des mises à jour.",
    "commandRequirementsNotAPlayer": "&cCette commande nécessite que l'exécuteur soit un joueur.",
    "commandRequirementsDontHaveAction": "&cVotre faction ne vous permet pas de faire cela, elle nécessite l'action %1$s.",
    "commandBaseHelp": "&7La commande de base pour les factions.",
    "commandRequirementsNotAFactionMember": "&cCette commande nécessite que l'exécuteur soit membre d'une faction, créez la vôtre en utilisant \"/f create\".",
    "positionChangedTeleportWarmup": "&7Vous avez bougé, téléportation annulé.",
    "commandShowBarElement": "&8&m=",
    "commandAdminKickNotify": "&7Vous avez été &6expulsé&7 de votre faction par un administrateur.",
    "commandUpgradeGlobalUpgraded": "&6%1$s&7 a été mis à jour &6%2$s&7.",
    "messagePrefix": "&7[&6?&7] "
}
